LICENSE
MANIFEST.in
README.rst
greencode.py
setup.cfg
setup.py
greencode.egg-info/PKG-INFO
greencode.egg-info/SOURCES.txt
greencode.egg-info/dependency_links.txt
greencode.egg-info/top_level.txt