Metadata-Version: 1.1
Name: greencode
Version: 0.1
Summary: Green Code is a simple visual text representation that aims to be useful in LED grid based applications.
Home-page: http://ledui.github.io/
Author: Zeth
Author-email: theology@gmail.com
License: BSD
Platform: UNKNOWN
Classifier: Programming Language :: Python :: 2.7
Classifier: Programming Language :: Python :: 3
Classifier: Intended Audience :: Developers
Classifier: License :: OSI Approved :: BSD License
Classifier: Topic :: Software Development :: Libraries
Classifier: Topic :: Utilities
